ez_wikidata/__init__.py
ez_wikidata/trulytabular.py
ez_wikidata/version.py
ez_wikidata/wbquery.py
ez_wikidata/wdproperty.py
ez_wikidata/wdsearch.py
ez_wikidata/wikidata.py
ez_wikidata/resources/sb_props.yaml
ez_wikidata/resources/wdprops.json
py_ez_wikidata-0.4.0.dist-info/METADATA
py_ez_wikidata-0.4.0.dist-info/WHEEL
py_ez_wikidata-0.4.0.dist-info/entry_points.txt
py_ez_wikidata-0.4.0.dist-info/licenses/LICENSE
py_ez_wikidata-0.4.0.dist-info/RECORD
