Metadata-Version: 2.4
Name: py_ez_wikidata
Version: 0.4.0
Summary: python wikidata access via dicts
Project-URL: Home, https://github.com/WolfgangFahl/py_ez_wikidata
Project-URL: Documentation, https://wiki.bitplan.com/index.php/Py_ez_wikidata
Project-URL: Source, https://github.com/WolfgangFahl/py_ez_wikidata
Author-email: Wolfgang Fahl <wf@WolfgangFahl.com>
Maintainer-email: Wolfgang Fahl <wf@WolfgangFahl.com>
License: Apache-2.0
License-File: LICENSE
Keywords: wikidata
Classifier: Development Status :: 4 - Beta
Classifier: Environment :: Web Environment
Classifier: Intended Audience :: Developers
Classifier: Intended Audience :: Education
Classifier: Intended Audience :: Science/Research
Classifier: License :: OSI Approved :: Apache Software License
Classifier: Operating System :: OS Independent
Classifier: Programming Language :: Python :: 3 :: Only
Classifier: Programming Language :: Python :: 3.10
Classifier: Programming Language :: Python :: 3.11
Classifier: Programming Language :: Python :: 3.12
Classifier: Programming Language :: Python :: 3.13
Classifier: Topic :: Software Development :: User Interfaces
Requires-Python: >=3.10
Requires-Dist: pybasemkit>=0.1.6
Requires-Dist: pylodstorage>=0.18.7
Requires-Dist: wikibaseintegrator>=0.12.15
Provides-Extra: test
Requires-Dist: green; extra == 'test'
